randcraft/__init__.py
randcraft/anonymous.py
randcraft/constructors.py
randcraft/misc.py
randcraft/models.py
randcraft/observations.py
randcraft/pdf_convolver.py
randcraft/random_variable.py
randcraft/rvs/__init__.py
randcraft/rvs/anonymous.py
randcraft/rvs/base.py
randcraft/rvs/continuous.py
randcraft/rvs/discrete.py
randcraft/rvs/gaussian_kde.py
randcraft/rvs/mixture.py
randcraft/rvs/multi.py
randcraft/rvs/scipy_pdf.py
randcraft/utils/__init__.py
randcraft/utils/arrays.py
randcraft/utils/fft_convolve.py
randcraft-0.1.10.dist-info/METADATA
randcraft-0.1.10.dist-info/WHEEL
randcraft-0.1.10.dist-info/licenses/LICENSE
randcraft-0.1.10.dist-info/RECORD
