Metadata-Version: 2.4
Name: randcraft
Version: 0.1.10
Summary: An object-oriented approach to defining and combining random variables
Project-URL: Homepage, https://github.com/RobbieKiwi/RandCraft/
Project-URL: PyPI, https://pypi.org/project/randcraft/
License-File: LICENSE
Requires-Python: >=3.12
Requires-Dist: matplotlib>=3.10.6
Requires-Dist: numpy>=2.3.3
Requires-Dist: scipy>=1.16.1
